[{
  "open": 50.48,
  "low": 48.01,
  "date": "2016-12-31",
  "close": 48.1,
  "high": 50.48
}, {
  "open": 50.52,
  "low": 49.97,
  "date": "2016-12-30",
  "close": 50.38,
  "high": 52.24
}, {
  "open": 48.43,
  "low": 48.43,
  "date": "2016-12-29",
  "close": 50.99,
  "high": 52.93
}, {
  "open": 44.02,
  "low": 43.72,
  "date": "2016-12-28",
  "close": 48.49,
  "high": 54.11
}, {
  "open": 43.5,
  "low": 42.16,
  "date": "2016-12-27",
  "close": 44.38,
  "high": 48.31
}, {
  "open": 45.89,
  "low": 42.67,
  "date": "2016-12-26",
  "close": 43.59,
  "high": 46.91
}, {
  "open": 48.52,
  "low": 44.06,
  "date": "2016-12-25",
  "close": 45.85,
  "high": 50.01
}, {
  "open": 51.99,
  "low": 47.51,
  "date": "2016-12-24",
  "close": 48.24,
  "high": 54.89
}, {
  "open": 48.02,
  "low": 45.97,
  "date": "2016-12-23",
  "close": 52.05,
  "high": 63.97
}, {
  "open": 36.29,
  "low": 36.28,
  "date": "2016-12-22",
  "close": 47.76,
  "high": 48.57
}, {
  "open": 36.17,
  "low": 35.77,
  "date": "2016-12-21",
  "close": 36.29,
  "high": 39.32
}, {
  "open": 34.55,
  "low": 34.24,
  "date": "2016-12-20",
  "close": 36.02,
  "high": 40.06
}, {
  "open": 36.55,
  "low": 33.91,
  "date": "2016-12-19",
  "close": 34.47,
  "high": 37.48
}, {
  "open": 35.82,
  "low": 35.14,
  "date": "2016-12-18",
  "close": 36.44,
  "high": 40.63
}, {
  "open": 40.22,
  "low": 35.8,
  "date": "2016-12-17",
  "close": 35.84,
  "high": 40.22
}, {
  "open": 40.48,
  "low": 40.06,
  "date": "2016-12-16",
  "close": 40.22,
  "high": 42.3
}, {
  "open": 44.41,
  "low": 40.08,
  "date": "2016-12-15",
  "close": 40.31,
  "high": 44.41
}, {
  "open": 46.82,
  "low": 43.13,
  "date": "2016-12-14",
  "close": 44.33,
  "high": 47.24
}, {
  "open": 50.02,
  "low": 46.55,
  "date": "2016-12-13",
  "close": 46.78,
  "high": 50.02
}, {
  "open": 48.48,
  "low": 48.33,
  "date": "2016-12-12",
  "close": 49.92,
  "high": 50.12
}, {
  "open": 49.6,
  "low": 48.34,
  "date": "2016-12-11",
  "close": 48.48,
  "high": 50.56
}, {
  "open": 50.35,
  "low": 48.11,
  "date": "2016-12-10",
  "close": 49.78,
  "high": 50.54
}, {
  "open": 53.38,
  "low": 49.7,
  "date": "2016-12-09",
  "close": 50.37,
  "high": 53.44
}, {
  "open": 54.0,
  "low": 53.28,
  "date": "2016-12-08",
  "close": 53.3,
  "high": 57.45
}, {
  "open": 48.74,
  "low": 47.71,
  "date": "2016-12-07",
  "close": 54.61,
  "high": 61.18
}, {
  "open": 50.97,
  "low": 47.48,
  "date": "2016-12-06",
  "close": 48.74,
  "high": 53.08
}, {
  "open": 58.39,
  "low": 50.81,
  "date": "2016-12-05",
  "close": 50.93,
  "high": 58.59
}, {
  "open": 59.46,
  "low": 58.35,
  "date": "2016-12-04",
  "close": 58.39,
  "high": 62.11
}, {
  "open": 59.85,
  "low": 58.66,
  "date": "2016-12-03",
  "close": 59.53,
  "high": 60.85
}, {
  "open": 63.63,
  "low": 60.32,
  "date": "2016-12-02",
  "close": 60.32,
  "high": 64.5
}, {
  "open": 68.46,
  "low": 62.49,
  "date": "2016-12-01",
  "close": 63.03,
  "high": 68.46
}, {
  "open": 68.76,
  "low": 66.71,
  "date": "2016-11-30",
  "close": 68.69,
  "high": 72.94
}, {
  "open": 71.84,
  "low": 67.96,
  "date": "2016-11-29",
  "close": 68.72,
  "high": 77.66
}, {
  "open": 69.26,
  "low": 66.21,
  "date": "2016-11-28",
  "close": 70.96,
  "high": 75.52
}, {
  "open": 77.33,
  "low": 66.66,
  "date": "2016-11-27",
  "close": 69.83,
  "high": 80.42
}, {
  "open": 91.13,
  "low": 76.02,
  "date": "2016-11-26",
  "close": 77.3,
  "high": 92.36
}, {
  "open": 96.64,
  "low": 88.17,
  "date": "2016-11-25",
  "close": 91.33,
  "high": 106.89
}, {
  "open": 78.43,
  "low": 69.08,
  "date": "2016-11-24",
  "close": 97.19,
  "high": 102.42
}, {
  "open": 57.54,
  "low": 57.4,
  "date": "2016-11-23",
  "close": 77.56,
  "high": 87.68
}, {
  "open": 54.01,
  "low": 53.39,
  "date": "2016-11-22",
  "close": 57.9,
  "high": 72.02
}, {
  "open": 59.96,
  "low": 53.94,
  "date": "2016-11-21",
  "close": 54.02,
  "high": 60.23
}, {
  "open": 65.29,
  "low": 60.27,
  "date": "2016-11-20",
  "close": 60.27,
  "high": 67.63
}, {
  "open": 71.12,
  "low": 64.63,
  "date": "2016-11-19",
  "close": 65.7,
  "high": 72.0
}, {
  "open": 87.33,
  "low": 70.47,
  "date": "2016-11-18",
  "close": 70.64,
  "high": 88.84
}, {
  "open": 97.48,
  "low": 85.39,
  "date": "2016-11-17",
  "close": 87.64,
  "high": 100.42
}, {
  "open": 109.71,
  "low": 96.92,
  "date": "2016-11-16",
  "close": 96.95,
  "high": 115.62
}, {
  "open": 105.16,
  "low": 97.43,
  "date": "2016-11-15",
  "close": 109.34,
  "high": 131.22
}, {
  "open": 117.55,
  "low": 97.18,
  "date": "2016-11-14",
  "close": 105.06,
  "high": 117.82
}, {
  "open": 143.17,
  "low": 117.26,
  "date": "2016-11-13",
  "close": 117.26,
  "high": 146.23
}, {
  "open": 183.02,
  "low": 144.11,
  "date": "2016-11-12",
  "close": 144.11,
  "high": 189.54
}, {
  "open": 224.67,
  "low": 183.24,
  "date": "2016-11-11",
  "close": 183.36,
  "high": 226.17
}, {
  "open": 254.94,
  "low": 224.83,
  "date": "2016-11-10",
  "close": 226.17,
  "high": 257.49
}, {
  "open": 331.69,
  "low": 222.51,
  "date": "2016-11-09",
  "close": 255.58,
  "high": 374.12
}, {
  "open": 233.78,
  "low": 178.98,
  "date": "2016-11-08",
  "close": 308.64,
  "high": 308.64
}, {
  "open": 319.23,
  "low": 236.0,
  "date": "2016-11-07",
  "close": 236.0,
  "high": 345.94
}, {
  "open": 504.27,
  "low": 320.54,
  "date": "2016-11-06",
  "close": 321.79,
  "high": 507.5
}, {
  "open": 599.52,
  "low": 501.69,
  "date": "2016-11-05",
  "close": 504.57,
  "high": 634.0
}, {
  "open": 887.66,
  "low": 601.84,
  "date": "2016-11-04",
  "close": 603.98,
  "high": 889.8
}, {
  "open": 940.66,
  "low": 863.81,
  "date": "2016-11-03",
  "close": 887.26,
  "high": 1067.59
}, {
  "open": 1326.29,
  "low": 872.41,
  "date": "2016-11-02",
  "close": 942.78,
  "high": 1409.07
}, {
  "open": 1599.72,
  "low": 1189.33,
  "date": "2016-11-01",
  "close": 1333.74,
  "high": 2027.05
}, {
  "open": 570.91,
  "low": 472.73,
  "date": "2016-10-31",
  "close": 1624.58,
  "high": 2217.64
}, {
  "open": 2014.38,
  "low": 504.54,
  "date": "2016-10-30",
  "close": 574.82,
  "high": 2028.46
}, {
  "open": 4293.37,
  "low": 2006.47,
  "date": "2016-10-29",
  "close": 2044.47,
  "high": 5941.8
}]